[
  {
    "id": 0,
    "type": "move",
    "duration": 266,
    "total_distance": 1224.0,
    "ease_in": "cubic",
    "lock_input": true,
    "comment": "rainbow transition up"
  },
  {
    "id": 1,
    "type": "move",
    "duration": 300,
    "total_distance": {
      "reference_id": 0,
      "property": "total_distance"
    },
    "ease_in": "cubic",
    "ease_out": "exponential",
    "comment": "chara left/right up"
  },
  {
    "id": 2,
    "type": "move",
    "duration": 33,
    "total_distance": 45.0,
    "delay": {
      "reference_id": 1,
      "property": "duration"
    },
    "comment": "chara left/right down"
  },
  {
    "id": 3,
    "type": "fade",
    "duration": {
      "reference_id": 0,
      "property": "duration"
    },
    "initial_opacity": 0.0,
    "final_opacity": 1.0,
    "delay": {
      "init_val": {
        "reference_id": 0,
        "property": "duration"
      },
      "reference_id": 0,
      "property": "duration"
    },
    "lock_input": true,
    "comment": "song text fade in"
  },
  {
    "id": 4,
    "type": "fade",
    "duration": 133,
    "comment": "song text fade out"
  },
  {
    "id": 5,
    "type": "move",
    "duration": 983.33,
    "total_distance": 540.0,
    "ease_out": "quadratic",
    "comment": "result shutter move in"
  },
  {
    "id": 6,
    "type": "fade",
    "duration": 500,
    "initial_opacity": 0.0,
    "final_opacity": 1.0,
    "loop": true,
    "delay": 500,
    "reverse_delay": 0,
    "comment": "indicator skip drum don fade in/out"
  },
  {
    "id": 7,
    "type": "move",
    "duration": 1000,
    "total_distance": 22.5,
    "loop": true,
    "comment": "indicator blue arrow move out"
  },
  {
    "id": 8,
    "type": "fade",
    "duration": 1000,
    "loop": true,
    "comment": "indicator blue arrow fade in/out"
  },
  {
    "id": 9,
    "type": "texture_resize",
    "duration": 333,
    "initial_size": 1.0,
    "final_size": 1.5,
    "reverse_delay": 0,
    "ease_out": "quadratic",
    "comment": "timer counter pop in/out"
  },
  {
    "id": 10,
    "type": "texture_resize",
    "duration": 200,
    "initial_size": 1.0,
    "final_size": 1.5,
    "comment": "timer highlight pop out"
  },
  {
    "id": 11,
    "type": "fade",
    "duration": 200,
    "comment": "timer highlight fade out"
  },
  {
    "id": 12,
    "type": "texture_change",
    "duration": 300,
    "textures": [
      [
        0.0,
        50,
        0
      ],
      [
        50,
        100,
        1
      ],
      [
        100,
        150,
        2
      ],
      [
        150,
        200,
        3
      ],
      [
        200,
        250,
        4
      ],
      [
        250,
        300,
        5
      ]
    ],
    "comment": "rainbow nameplate animation"
  }
]